ieltspeak/__about__.py
ieltspeak/__init__.py
ieltspeak/cli.py
ieltspeak/data_loader.py
ieltspeak/test.py
ieltspeak/update_data.py
ieltspeak/data/ielts_part0.json
ieltspeak/data/ielts_part1.json
ieltspeak-2025.9.2.dist-info/METADATA
ieltspeak-2025.9.2.dist-info/WHEEL
ieltspeak-2025.9.2.dist-info/entry_points.txt
ieltspeak-2025.9.2.dist-info/licenses/LICENSE.txt
ieltspeak-2025.9.2.dist-info/RECORD
