Metadata-Version: 2.4
Name: ieltspeak
Version: 2025.9.2
Summary: a CLI application that displays IELTS speaking questions.
Project-URL: Documentation, https://github.com/duzhuoshanwai/ieltspeak#readme
Project-URL: Issues, https://github.com/duzhuoshanwai/ieltspeak/issues
Project-URL: Source, https://github.com/duzhuoshanwai/ieltspeak
Author-email: duzhuoshanwai <duzhuo@saint1337.top>
License-Expression: MIT
License-File: LICENSE.txt
Keywords: IELTS
Classifier: Development Status :: 4 - Beta
Classifier: Programming Language :: Python
Classifier: Programming Language :: Python :: 3.11
Classifier: Programming Language :: Python :: 3.12
Classifier: Programming Language :: Python :: Implementation :: CPython
Classifier: Programming Language :: Python :: Implementation :: PyPy
Requires-Python: >=3.11
Requires-Dist: click>=8.2.1
Requires-Dist: httpx>=0.28.1
